{"shape": {"width": "500", "height": "330", "depth": "3"}, "objects": {"1": {"name": "person", "bbox": {"xmin": "397", "ymin": "107", "xmax": "498", "ymax": "327"}, "part": {"1": {"name": "head", "bbox": {"xmin": "433", "ymin": "109", "xmax": "462", "ymax": "138"}}, "2": {"name": "foot", "bbox": {"xmin": "464", "ymin": "307", "xmax": "491", "ymax": "321"}}, "3": {"name": "foot", "bbox": {"xmin": "388", "ymin": "299", "xmax": "413", "ymax": "319"}}}}, "2": {"name": "person", "bbox": {"xmin": "353", "ymin": "68", "xmax": "451", "ymax": "296"}, "part": {"1": {"name": "head", "bbox": {"xmin": "375", "ymin": "69", "xmax": "405", "ymax": "102"}}, "2": {"name": "hand", "bbox": {"xmin": "428", "ymin": "191", "xmax": "449", "ymax": "218"}}}}, "3": {"name": "person", "bbox": {"xmin": "261", "ymin": "87", "xmax": "403", "ymax": "330"}, "part": {"1": {"name": "head", "bbox": {"xmin": "319", "ymin": "91", "xmax": "359", "ymax": "134"}}, "2": {"name": "hand", "bbox": {"xmin": "261", "ymin": "236", "xmax": "277", "ymax": "265"}}}}}}