{"shape": {"width": "500", "height": "375", "depth": "3"}, "objects": {"1": {"name": "cow", "bbox": {"xmin": "1", "ymin": "107", "xmax": "37", "ymax": "238"}}, "2": {"name": "cow", "bbox": {"xmin": "110", "ymin": "97", "xmax": "264", "ymax": "194"}}, "3": {"name": "cow", "bbox": {"xmin": "250", "ymin": "94", "xmax": "359", "ymax": "183"}}, "4": {"name": "cow", "bbox": {"xmin": "383", "ymin": "96", "xmax": "423", "ymax": "175"}}, "5": {"name": "cow", "bbox": {"xmin": "464", "ymin": "75", "xmax": "500", "ymax": "132"}}, "6": {"name": "car", "bbox": {"xmin": "100", "ymin": "63", "xmax": "140", "ymax": "94"}}, "7": {"name": "car", "bbox": {"xmin": "329", "ymin": "55", "xmax": "374", "ymax": "91"}}, "8": {"name": "car", "bbox": {"xmin": "404", "ymin": "64", "xmax": "438", "ymax": "84"}}, "9": {"name": "car", "bbox": {"xmin": "440", "ymin": "69", "xmax": "485", "ymax": "83"}}}}