{"shape": {"width": "500", "height": "375", "depth": "3"}, "objects": {"1": {"name": "diningtable", "bbox": {"xmin": "1", "ymin": "144", "xmax": "385", "ymax": "375"}}, "2": {"name": "person", "bbox": {"xmin": "1", "ymin": "137", "xmax": "117", "ymax": "303"}}, "3": {"name": "person", "bbox": {"xmin": "47", "ymin": "76", "xmax": "155", "ymax": "242"}}, "4": {"name": "person", "bbox": {"xmin": "117", "ymin": "77", "xmax": "195", "ymax": "238"}}, "5": {"name": "person", "bbox": {"xmin": "173", "ymin": "73", "xmax": "229", "ymax": "186"}}, "6": {"name": "person", "bbox": {"xmin": "243", "ymin": "63", "xmax": "328", "ymax": "150"}}, "7": {"name": "person", "bbox": {"xmin": "339", "ymin": "69", "xmax": "401", "ymax": "198"}}, "8": {"name": "person", "bbox": {"xmin": "381", "ymin": "84", "xmax": "455", "ymax": "285"}}, "9": {"name": "person", "bbox": {"xmin": "400", "ymin": "134", "xmax": "500", "ymax": "375"}}, "10": {"name": "person", "bbox": {"xmin": "214", "ymin": "120", "xmax": "426", "ymax": "375"}}}}