{"shape": {"width": "500", "height": "375", "depth": "3"}, "objects": {"1": {"name": "aeroplane", "bbox": {"xmin": "18", "ymin": "29", "xmax": "500", "ymax": "356"}}, "2": {"name": "person", "bbox": {"xmin": "405", "ymin": "263", "xmax": "450", "ymax": "358"}}, "3": {"name": "person", "bbox": {"xmin": "448", "ymin": "265", "xmax": "487", "ymax": "360"}}, "4": {"name": "person", "bbox": {"xmin": "293", "ymin": "264", "xmax": "321", "ymax": "354"}}, "5": {"name": "person", "bbox": {"xmin": "315", "ymin": "275", "xmax": "333", "ymax": "352"}}, "6": {"name": "person", "bbox": {"xmin": "284", "ymin": "292", "xmax": "300", "ymax": "340"}}, "7": {"name": "person", "bbox": {"xmin": "244", "ymin": "301", "xmax": "258", "ymax": "340"}}}}