{"shape": {"width": "500", "height": "375", "depth": "3"}, "objects": {"1": {"name": "bicycle", "bbox": {"xmin": "330", "ymin": "149", "xmax": "369", "ymax": "178"}}, "2": {"name": "bicycle", "bbox": {"xmin": "142", "ymin": "174", "xmax": "280", "ymax": "325"}}, "3": {"name": "car", "bbox": {"xmin": "1", "ymin": "93", "xmax": "113", "ymax": "270"}}, "4": {"name": "car", "bbox": {"xmin": "1", "ymin": "138", "xmax": "206", "ymax": "245"}}, "5": {"name": "car", "bbox": {"xmin": "142", "ymin": "143", "xmax": "248", "ymax": "208"}}, "6": {"name": "car", "bbox": {"xmin": "209", "ymin": "142", "xmax": "279", "ymax": "196"}}, "7": {"name": "car", "bbox": {"xmin": "246", "ymin": "131", "xmax": "340", "ymax": "167"}}, "8": {"name": "car", "bbox": {"xmin": "396", "ymin": "127", "xmax": "435", "ymax": "147"}}, "9": {"name": "person", "bbox": {"xmin": "305", "ymin": "120", "xmax": "336", "ymax": "269"}}, "10": {"name": "person", "bbox": {"xmin": "259", "ymin": "120", "xmax": "330", "ymax": "303"}}}}