{"shape": {"width": "375", "height": "500", "depth": "3"}, "objects": {"1": {"name": "bicycle", "bbox": {"xmin": "265", "ymin": "351", "xmax": "375", "ymax": "460"}}, "2": {"name": "person", "bbox": {"xmin": "160", "ymin": "276", "xmax": "211", "ymax": "424"}}, "3": {"name": "pottedplant", "bbox": {"xmin": "263", "ymin": "351", "xmax": "316", "ymax": "439"}}, "4": {"name": "pottedplant", "bbox": {"xmin": "321", "ymin": "263", "xmax": "375", "ymax": "438"}}, "5": {"name": "pottedplant", "bbox": {"xmin": "319", "ymin": "108", "xmax": "375", "ymax": "128"}}}}