{"shape": {"depth": "3", "height": "375", "width": "500"}, "objects": {"1": {"name": "bus", "bbox": {"xmax": "500", "xmin": "426", "ymax": "203", "ymin": "116"}}, "2": {"name": "bus", "bbox": {"xmax": "439", "xmin": "350", "ymax": "197", "ymin": "116"}}, "3": {"name": "bus", "bbox": {"xmax": "362", "xmin": "280", "ymax": "188", "ymin": "115"}}, "4": {"name": "bus", "bbox": {"xmax": "22", "xmin": "1", "ymax": "266", "ymin": "34"}}, "5": {"name": "bus", "bbox": {"xmax": "33", "xmin": "23", "ymax": "204", "ymin": "122"}}, "6": {"name": "bus", "bbox": {"xmax": "59", "xmin": "42", "ymax": "192", "ymin": "129"}}, "7": {"name": "bus", "bbox": {"xmax": "441", "xmin": "59", "ymax": "327", "ymin": "36"}}, "8": {"name": "person", "bbox": {"xmax": "264", "xmin": "214", "ymax": "188", "ymin": "107"}}}}