{"shape": {"depth": "3", "height": "375", "width": "500"}, "objects": {"1": {"name": "car", "bbox": {"xmax": "486", "xmin": "452", "ymax": "248", "ymin": "229"}}, "2": {"name": "car", "bbox": {"xmax": "442", "xmin": "390", "ymax": "260", "ymin": "229"}}, "3": {"name": "bus", "bbox": {"xmax": "429", "xmin": "382", "ymax": "253", "ymin": "201"}}, "4": {"name": "bus", "bbox": {"xmax": "384", "xmin": "241", "ymax": "277", "ymin": "184"}}, "5": {"name": "car", "bbox": {"xmax": "250", "xmin": "130", "ymax": "299", "ymin": "239"}}, "6": {"name": "bus", "bbox": {"xmax": "247", "xmin": "27", "ymax": "278", "ymin": "177"}}, "7": {"name": "car", "bbox": {"xmax": "493", "xmin": "464", "ymax": "244", "ymin": "225"}}}}