{"shape": {"depth": "3", "height": "375", "width": "500"}, "objects": {"1": {"name": "car", "bbox": {"xmax": "319", "xmin": "200", "ymax": "47", "ymin": "11"}}, "2": {"name": "car", "bbox": {"xmax": "92", "xmin": "25", "ymax": "37", "ymin": "7"}}, "3": {"name": "car", "bbox": {"xmax": "457", "xmin": "1", "ymax": "374", "ymin": "85"}}, "4": {"name": "person", "bbox": {"xmax": "346", "xmin": "88", "ymax": "244", "ymin": "100"}}, "5": {"name": "car", "bbox": {"xmax": "123", "xmin": "88", "ymax": "38", "ymin": "11"}}, "6": {"name": "car", "bbox": {"xmax": "332", "xmin": "263", "ymax": "44", "ymin": "13"}}}}