{"shape": {"depth": "3", "height": "375", "width": "500"}, "objects": {"1": {"name": "person", "bbox": {"xmax": "374", "xmin": "95", "ymax": "375", "ymin": "190"}}, "2": {"name": "person", "bbox": {"xmax": "500", "xmin": "379", "ymax": "375", "ymin": "238"}}, "3": {"name": "person", "bbox": {"xmax": "464", "xmin": "351", "ymax": "375", "ymin": "201"}}, "4": {"name": "person", "bbox": {"xmax": "395", "xmin": "262", "ymax": "318", "ymin": "178"}}, "5": {"name": "person", "bbox": {"xmax": "197", "xmin": "111", "ymax": "289", "ymin": "187"}}, "6": {"name": "bottle", "bbox": {"xmax": "145", "xmin": "129", "ymax": "235", "ymin": "189"}}, "7": {"name": "person", "bbox": {"xmax": "293", "xmin": "259", "ymax": "260", "ymin": "195"}}, "8": {"name": "person", "bbox": {"xmax": "407", "xmin": "296", "ymax": "224", "ymin": "132"}}, "9": {"name": "person", "bbox": {"xmax": "384", "xmin": "348", "ymax": "241", "ymin": "211"}}, "10": {"name": "person", "bbox": {"xmax": "166", "xmin": "36", "ymax": "364", "ymin": "239"}}}}