{"shape": {"depth": "3", "height": "362", "width": "500"}, "objects": {"1": {"name": "person", "bbox": {"xmax": "441", "xmin": "356", "ymax": "341", "ymin": "166"}, "part": {"1": {"name": "head", "bbox": {"xmin": "389", "ymin": "167", "xmax": "425", "ymax": "196"}}, "2": {"name": "hand", "bbox": {"xmin": "358", "ymin": "249", "xmax": "373", "ymax": "258"}}, "3": {"name": "hand", "bbox": {"xmin": "430", "ymin": "254", "xmax": "440", "ymax": "269"}}, "4": {"name": "foot", "bbox": {"xmin": "415", "ymin": "327", "xmax": "440", "ymax": "341"}}, "5": {"name": "foot", "bbox": {"xmin": "380", "ymin": "307", "xmax": "394", "ymax": "334"}}}}, "2": {"name": "person", "bbox": {"xmax": "108", "xmin": "27", "ymax": "362", "ymin": "154"}, "part": {"1": {"name": "head", "bbox": {"xmin": "46", "ymin": "154", "xmax": "87", "ymax": "189"}}, "2": {"name": "hand", "bbox": {"xmin": "30", "ymin": "264", "xmax": "43", "ymax": "278"}}, "3": {"name": "hand", "bbox": {"xmin": "94", "ymin": "261", "xmax": "106", "ymax": "275"}}, "4": {"name": "foot", "bbox": {"xmin": "56", "ymin": "346", "xmax": "72", "ymax": "362"}}, "5": {"name": "foot", "bbox": {"xmin": "70", "ymin": "334", "xmax": "81", "ymax": "352"}}}}}}