{"shape": {"depth": "3", "height": "311", "width": "500"}, "objects": {"1": {"name": "person", "bbox": {"xmax": "315", "xmin": "242", "ymax": "292", "ymin": "125"}, "part": {"1": {"name": "head", "bbox": {"xmin": "257", "ymin": "125", "xmax": "277", "ymax": "156"}}, "2": {"name": "hand", "bbox": {"xmin": "248", "ymin": "201", "xmax": "262", "ymax": "218"}}, "3": {"name": "hand", "bbox": {"xmin": "279", "ymin": "198", "xmax": "290", "ymax": "215"}}, "4": {"name": "foot", "bbox": {"xmin": "262", "ymin": "271", "xmax": "279", "ymax": "288"}}, "5": {"name": "foot", "bbox": {"xmin": "290", "ymin": "276", "xmax": "314", "ymax": "290"}}}}}}