{"shape": {"depth": "3", "height": "375", "width": "500"}, "objects": {"1": {"name": "pottedplant", "bbox": {"xmax": "500", "xmin": "391", "ymax": "234", "ymin": "149"}}, "2": {"name": "chair", "bbox": {"xmax": "273", "xmin": "192", "ymax": "309", "ymin": "172"}}, "3": {"name": "chair", "bbox": {"xmax": "330", "xmin": "269", "ymax": "252", "ymin": "170"}}, "4": {"name": "chair", "bbox": {"xmax": "379", "xmin": "250", "ymax": "369", "ymin": "176"}}, "5": {"name": "sofa", "bbox": {"xmax": "51", "xmin": "1", "ymax": "374", "ymin": "193"}}, "6": {"name": "sofa", "bbox": {"xmax": "498", "xmin": "350", "ymax": "371", "ymin": "224"}}}}