{"shape": {"depth": "3", "height": "375", "width": "500"}, "objects": {"1": {"name": "pottedplant", "bbox": {"xmax": "114", "xmin": "9", "ymax": "98", "ymin": "10"}}, "2": {"name": "pottedplant", "bbox": {"xmax": "214", "xmin": "107", "ymax": "207", "ymin": "160"}}, "3": {"name": "pottedplant", "bbox": {"xmax": "375", "xmin": "284", "ymax": "207", "ymin": "166"}}, "4": {"name": "bottle", "bbox": {"xmax": "500", "xmin": "489", "ymax": "238", "ymin": "183"}}, "5": {"name": "bottle", "bbox": {"xmax": "490", "xmin": "467", "ymax": "235", "ymin": "201"}}, "6": {"name": "chair", "bbox": {"xmax": "343", "xmin": "273", "ymax": "274", "ymin": "202"}}, "7": {"name": "chair", "bbox": {"xmax": "226", "xmin": "173", "ymax": "375", "ymin": "231"}}, "8": {"name": "diningtable", "bbox": {"xmax": "499", "xmin": "204", "ymax": "374", "ymin": "270"}}, "9": {"name": "chair", "bbox": {"xmax": "244", "xmin": "203", "ymax": "375", "ymin": "276"}}, "10": {"name": "bottle", "bbox": {"xmax": "499", "xmin": "484", "ymax": "236", "ymin": "210"}}}}